nir/__init__.py
nir/serialization.py
nir/ir/__init__.py
nir/ir/conv.py
nir/ir/delay.py
nir/ir/flatten.py
nir/ir/graph.py
nir/ir/linear.py
nir/ir/neuron.py
nir/ir/node.py
nir/ir/pooling.py
nir/ir/threshold.py
nir/ir/typing.py
nir/ir/utils.py
nir-1.0.7.dist-info/licenses/LICENSE
nir-1.0.7.dist-info/METADATA
nir-1.0.7.dist-info/WHEEL
nir-1.0.7.dist-info/top_level.txt
nir-1.0.7.dist-info/RECORD
