Metadata-Version: 2.4
Name: nir
Version: 1.0.7
Summary: Neuromorphic Intermediate Representation
Author-email: Steven Abreu <s.abreu@rug.nl>, Felix Bauer <felix.bauer@synsense.ai>, Jason Eshraghian <jeshragh@ucsc.edu>, Matthias Jobst <matthias.jobst2@tu-dresden.de>, Gregor Lenz <mail@lenzgregor.com>, Jens Egholm Pedersen <jens@jepedersen.dk>, Sadique Sheik <sadique.sheik@synsense.ai>
Project-URL: homepage, https://github.com/neuromorphs/nir
Keywords: neuromorphic,intermediate,representation
Classifier: Development Status :: 1 - Planning
Classifier: Intended Audience :: Developers
Classifier: Intended Audience :: Science/Research
Classifier: License :: OSI Approved :: BSD License
Classifier: Programming Language :: Python :: 3
Classifier: Topic :: Scientific/Engineering :: Artificial Intelligence
Classifier: Topic :: Scientific/Engineering :: Information Analysis
Classifier: Topic :: Scientific/Engineering :: Mathematics
Classifier: Topic :: Scientific/Engineering :: Physics
Classifier: Topic :: Software Development :: Libraries :: Python Modules
Requires-Python: >=3.9
License-File: LICENSE
Requires-Dist: numpy
Requires-Dist: h5py
Dynamic: license-file
